continuedfractions-1.11.0.dist-info/METADATA
continuedfractions-1.11.0.dist-info/WHEEL
continuedfractions-1.11.0.dist-info/entry_points.txt
continuedfractions-1.11.0.dist-info/licenses/LICENSE
continuedfractions/__version__.py
continuedfractions/continuedfraction.py
continuedfractions/lib.py
continuedfractions/rational_points.py
continuedfractions/sequences.py
continuedfractions/utils.py
continuedfractions-1.11.0.dist-info/RECORD
