Metadata-Version: 2.1
Name: continuedfractions
Version: 1.11.0
Summary: Object-oriented continued fractions with Python.
Keywords: computational number theory,coprime integers,continued fractions,enumeration,farey sequences,fractions,irrational numbers,mediants,number theory,rational approximation,rational numbers,rational points,sequences,real numbers
Author-Email: "S. R. Murthy" <s.murthy@tutanota.com>
Maintainer-Email: "S. R. Murthy" <s.murthy@tutanota.com>
License:                     GNU GENERAL PUBLIC LICENSE
Classifier: Environment :: Console
Classifier: License :: OSI Approved :: Mozilla Public License 2.0 (MPL 2.0)
Classifier: Programming Language :: Python :: 3
Classifier: Programming Language :: Python :: 3.10
Classifier: Programming Language :: Python :: 3.11
Classifier: Programming Language :: Python :: 3.12
Classifier: Programming Language :: Python :: 3.13
Classifier: Development Status :: 5 - Production/Stable
Classifier: Operating System :: POSIX :: Linux
Classifier: Operating System :: MacOS
Classifier: Operating System :: Microsoft :: Windows
Project-URL: Homepage, https://github.com/sr-murthy/continuedfractions
Project-URL: Documentation, https://continuedfractions.readthedocs.io
Project-URL: Repository, https://github.com/sr-murthy/continuedfractions
Requires-Python: >=3.10
Provides-Extra: user
Requires-Dist: jupyter; extra == "user"
